alphacube/__init__.py
alphacube/_evaluator.py
alphacube/_validator.py
alphacube/cli.py
alphacube/core.py
alphacube/env.py
alphacube/model.py
alphacube/search.py
alphacube/utils.py
alphacube-0.1.5.dist-info/licenses/LICENSE
alphacube-0.1.5.dist-info/METADATA
alphacube-0.1.5.dist-info/WHEEL
alphacube-0.1.5.dist-info/entry_points.txt
alphacube-0.1.5.dist-info/top_level.txt
alphacube-0.1.5.dist-info/RECORD
