Metadata-Version: 2.4
Name: alphacube
Version: 0.1.5
Summary: A powerful & flexible Rubik's Cube solver
Author: Kyo Takano
License: MIT License
Project-URL: Documentation, https://alphacube.dev/docs/index.html
Project-URL: Source, https://github.com/kyo-takano/alphacube
Keywords: rubiks-cube,solver,ai
Classifier: Development Status :: 4 - Beta
Classifier: Intended Audience :: Developers
Classifier: License :: OSI Approved :: MIT License
Classifier: Programming Language :: Python :: 3
Classifier: Programming Language :: Python :: 3 :: Only
Classifier: Programming Language :: Python :: 3.6
Classifier: Programming Language :: Python :: 3.7
Classifier: Programming Language :: Python :: 3.8
Classifier: Programming Language :: Python :: 3.9
Classifier: Programming Language :: Python :: 3.10
Classifier: Programming Language :: Python :: 3.11
Requires-Python: >=3.6
License-File: LICENSE
Requires-Dist: torch>=2.0.1
Requires-Dist: numpy>=1.23.3
Requires-Dist: rich>=13.0.1
Requires-Dist: pydantic>=2.0.3
Requires-Dist: requests>=2.28.2
Requires-Dist: tqdm
Provides-Extra: eval
Requires-Dist: matplotlib; extra == "eval"
Requires-Dist: pandas; extra == "eval"
Requires-Dist: scikit-learn; extra == "eval"
Provides-Extra: test
Requires-Dist: pytest>=7.0; extra == "test"
Dynamic: license-file
